bx_django_utils/__init__.py
bx_django_utils/cached_dataclasses.py
bx_django_utils/filename.py
bx_django_utils/http.py
bx_django_utils/json_utils.py
bx_django_utils/stacktrace.py
bx_django_utils/translation.py
bx_django_utils/version.py
bx_django_utils/admin_extra_views/README.md
bx_django_utils/admin_extra_views/__init__.py
bx_django_utils/admin_extra_views/admin_config.py
bx_django_utils/admin_extra_views/apps.py
bx_django_utils/admin_extra_views/autodiscover.py
bx_django_utils/admin_extra_views/base_view.py
bx_django_utils/admin_extra_views/checks.py
bx_django_utils/admin_extra_views/conditions.py
bx_django_utils/admin_extra_views/datatypes.py
bx_django_utils/admin_extra_views/registry.py
bx_django_utils/admin_extra_views/site.py
bx_django_utils/admin_extra_views/utils.py
bx_django_utils/admin_extra_views/views.py
bx_django_utils/admin_extra_views/management/__init__.py
bx_django_utils/admin_extra_views/management/commands/__init__.py
bx_django_utils/admin_extra_views/management/commands/admin_extra_views.py
bx_django_utils/admin_extra_views/management/commands/determine_version.py
bx_django_utils/admin_extra_views/tests/__init__.py
bx_django_utils/admin_extra_views/tests/test_admin_extra_views.py
bx_django_utils/admin_extra_views/tests/test_admin_extra_views_superuser_access_1.snapshot.json
bx_django_utils/admin_utils/__init__.py
bx_django_utils/admin_utils/admin_urls.py
bx_django_utils/admin_utils/filters.py
bx_django_utils/admin_utils/log_entry.py
bx_django_utils/admin_utils/tests/__init__.py
bx_django_utils/admin_utils/tests/test_log_entry.py
bx_django_utils/approve_workflow/__init__.py
bx_django_utils/approve_workflow/admin.py
bx_django_utils/approve_workflow/constants.py
bx_django_utils/approve_workflow/forms.py
bx_django_utils/approve_workflow/models.py
bx_django_utils/approve_workflow/locale/de/LC_MESSAGES/django.mo
bx_django_utils/approve_workflow/locale/de/LC_MESSAGES/django.po
bx_django_utils/approve_workflow/locale/en/LC_MESSAGES/django.mo
bx_django_utils-91.dist-info/METADATA
bx_django_utils-91.dist-info/WHEEL
bx_django_utils-91.dist-info/entry_points.txt
bx_django_utils-91.dist-info/licenses/LICENSE
bx_django_utils-91.dist-info/RECORD
