Metadata-Version: 2.4
Name: bx_django_utils
Version: 91
Summary: Various Django utility functions
Project-URL: Documentation, https://github.com/boxine/bx_django_utils/
Project-URL: Source, https://github.com/boxine/bx_django_utils/
Author-email: Jens Diemer <jens.diemer@boxine.de>, Philipp Hagemeister <phihag@phihag.de>, Florian Braun <mail@chiron-online.de>, Christian Schneider <christian@cnschn.com>
License: MIT
License-File: LICENSE
Classifier: Development Status :: 5 - Production/Stable
Classifier: Framework :: Django
Classifier: Intended Audience :: Developers
Classifier: Programming Language :: Python :: 3 :: Only
Classifier: Programming Language :: Python :: 3.10
Classifier: Programming Language :: Python :: 3.11
Classifier: Programming Language :: Python :: 3.12
Classifier: Programming Language :: Python :: 3.13
Classifier: Topic :: Software Development :: Libraries :: Python Modules
Requires-Python: >=3.11
Requires-Dist: bx-py-utils>=92
Requires-Dist: django>=4.2
Requires-Dist: python-stdnum
